korean_romanizer/__init__.py
korean_romanizer/cli.py
korean_romanizer/pronouncer.py
korean_romanizer/romanizer.py
korean_romanizer/syllable.py
korean_romanizer-0.28.0.dist-info/licenses/COPYING
korean_romanizer-0.28.0.dist-info/licenses/LICENSE
korean_romanizer-0.28.0.dist-info/METADATA
korean_romanizer-0.28.0.dist-info/WHEEL
korean_romanizer-0.28.0.dist-info/entry_points.txt
korean_romanizer-0.28.0.dist-info/top_level.txt
korean_romanizer-0.28.0.dist-info/RECORD
