Metadata-Version: 2.4
Name: korean_romanizer
Version: 0.28.0
Summary: A Python library for Korean romanization
Home-page: https://github.com/osori/korean-romanizer
Author: Ilkyu Ju
Author-email: ju.ilkyu@gmail.com
License: GNU GPLv3
Keywords: Korean,Romanization,Transliteration
Classifier: Development Status :: 3 - Alpha
Classifier: Intended Audience :: Developers
Classifier: Topic :: Software Development :: Libraries :: Python Modules
Classifier: License :: OSI Approved :: GNU General Public License v3 or later (GPLv3+)
Classifier: Programming Language :: Python :: 3
Classifier: Programming Language :: Python :: 3.4
Classifier: Programming Language :: Python :: 3.5
Classifier: Programming Language :: Python :: 3.6
License-File: LICENSE
License-File: COPYING
Dynamic: author
Dynamic: author-email
Dynamic: classifier
Dynamic: home-page
Dynamic: keywords
Dynamic: license
Dynamic: license-file
Dynamic: summary
